api_helper_saurabh/__init__.py
api_helper_saurabh/api_helper.py
api_helper_saurabh/data/sets.py
api_helper_saurabh/features/dates.py
api_helper_saurabh/models/null.py
api_helper_saurabh/models/performance.py
api_helper_saurabh-2025.0.2.0.dist-info/LICENSE
api_helper_saurabh-2025.0.2.0.dist-info/METADATA
api_helper_saurabh-2025.0.2.0.dist-info/WHEEL
api_helper_saurabh-2025.0.2.0.dist-info/RECORD
