Metadata-Version: 2.3
Name: api_helper_saurabh
Version: 2025.0.2.0
Summary: A package for converting api calls to pandas dataframe. Updated for python version
License: MIT
Author: Saurabh Sabharwal
Requires-Python: >=3.10,<4.0
Classifier: License :: OSI Approved :: MIT License
Classifier: Programming Language :: Python :: 3
Classifier: Programming Language :: Python :: 3.10
Classifier: Programming Language :: Python :: 3.11
Classifier: Programming Language :: Python :: 3.12
Classifier: Programming Language :: Python :: 3.13
Requires-Dist: pandas (>=2.0,<3.0)
Requires-Dist: requests (>=2.31,<3.0)
